ddparo/__init__.py
ddparo/ddparo.py
ddparo-0.5.0.dist-info/METADATA
ddparo-0.5.0.dist-info/WHEEL
ddparo-0.5.0.dist-info/entry_points.txt
ddparo-0.5.0.dist-info/top_level.txt
ddparo-0.5.0.dist-info/RECORD
