Metadata-Version: 2.1
Name: ddparo
Version: 0.5.0
Requires-Dist: requests
Requires-Dist: pyperclip
